chempy/__init__.py
chempy/arc.py
chempy/bond_amber.py
chempy/bond_mmff.py
chempy/bonds.py
chempy/brick.py
chempy/cc1.py
chempy/charge.py
chempy/cif.py
chempy/cpv.py
chempy/dictdb.py
chempy/gamess1.py
chempy/gms.py
chempy/hetatm.py
chempy/io.py
chempy/lst.py
chempy/mae.py
chempy/map.py
chempy/mass.py
chempy/mmd.py
chempy/models.py
chempy/mol.py
chempy/mol2.py
chempy/neighbor.py
chempy/pdb.py
chempy/pkl.py
chempy/place.py
chempy/protein.py
chempy/protein_amber.py
chempy/protein_amber99.py
chempy/protein_mmff.py
chempy/protein_residues.py
chempy/sdf.py
chempy/solvate.py
chempy/water_amber.py
chempy/water_residues.py
chempy/xyz.py
chempy/bmin/__init__.py
chempy/bmin/commands.py
chempy/bmin/realtime.py
chempy/bmin/state.py
chempy/bmin/util.py
chempy/champ/__init__.py
chempy/champ/amber99.py
chempy/champ/assign.py
chempy/champ/formal_charges.py
chempy/fast/__init__.py
chempy/fragments/__init__.py
chempy/mmtf/__init__.py
chempy/mmtf/io.py
chempy/tinker/__init__.py
chempy/tinker/amber.py
chempy/tinker/keyword.py
chempy/tinker/realtime.py
chempy/tinker/state.py
pmg_qt/TextEditor.py
pmg_qt/__init__.py
pmg_qt/advanced_settings_gui.py
pmg_qt/builder.py
pmg_qt/file_dialogs.py
pmg_qt/keymapping.py
pmg_qt/mimic_pmg_tk.py
pmg_qt/mimic_tk.py
pmg_qt/properties_dialog.py
pmg_qt/pymol_gl_widget.py
pmg_qt/pymol_qt_gui.py
pmg_qt/scene_bin_gui.py
pmg_qt/shortcut_menu_gui.py
pmg_qt/volume.py
pmg_qt/forms/__init__.py
pmg_qt/forms/askpartial.ui
pmg_qt/forms/change_confirm.ui
pmg_qt/forms/colors.ui
pmg_qt/forms/create_shortcut.ui
pmg_qt/forms/fetch.ui
pmg_qt/forms/help_shortcut.ui
pmg_qt/forms/load_aln.ui
pmg_qt/forms/load_mae.ui
pmg_qt/forms/load_map.ui
pmg_qt/forms/load_mtz.ui
pmg_qt/forms/load_traj.ui
pmg_qt/forms/movieexport.ui
pmg_qt/forms/pluginitem.ui
pmg_qt/forms/pluginmanager.ui
pmg_qt/forms/png.ui
pmg_qt/forms/props.ui
pmg_qt/forms/render.ui
pmg_qt/forms/save_molecule.ui
pymol_open_source_whl-3.1.0.4.dist-info/METADATA
pymol_open_source_whl-3.1.0.4.dist-info/WHEEL
pymol_open_source_whl-3.1.0.4.dist-info/RECORD
pymol_open_source_whl-3.1.0.4.dist-info/licenses/AUTHORS
pymol_open_source_whl-3.1.0.4.dist-info/licenses/LICENSE
