Metadata-Version: 2.2
Name: pymol-open-source-whl
Version: 3.1.0.4
Author-Email: Martin Urban <martin.urban@studmail.w-hs.de>
License: 
Project-URL: Documentation, https://pymolwiki.org/index.php/Main_Page
Project-URL: Repository, https://github.com/urban233/pymol-open-source-whl
Requires-Python: >=3.10
Requires-Dist: numpy==1.26.4
Provides-Extra: dev
Requires-Dist: pillow==10.3.0; extra == "dev"
Requires-Dist: pytest==8.2.2; extra == "dev"
